semirings/__init__.py
semirings/base.py
semirings/boolean.py
semirings/cutsets.py
semirings/float.py
semirings/fsa.py
semirings/interval.py
semirings/kleene.py
semirings/lazysort.py
semirings/logval.py
semirings/maxplus.py
semirings/maxtimes.py
semirings/mert.py
semirings/minplus.py
semirings/mintimes.py
semirings/misc.py
semirings/regex.py
semirings/sample.py
semirings/wfsa.py
semirings-0.3.1.dist-info/METADATA
semirings-0.3.1.dist-info/WHEEL
semirings-0.3.1.dist-info/top_level.txt
semirings-0.3.1.dist-info/RECORD
